README.md
drfhumplib/__init__.py
drfhumplib/parsers.py
drfhumplib/renders.py
drfhumplib-0.1.4.1.dist-info/WHEEL
drfhumplib-0.1.4.1.dist-info/METADATA
drfhumplib-0.1.4.1.dist-info/RECORD
